{
  "fabric:load_conditions": [
    {
      "condition": "fabric:and",
      "values": [
        {
          "condition": "fabric:all_mods_loaded",
          "values": [
            "create",
            "garnished"
          ]
        },
        {
          "condition": "fabric:not",
          "value": {
            "condition": "fabric:all_mods_loaded",
            "values": [
              "garnishedstoneautomation"
            ]
          }
        }
      ]
    }
  ],
  "type": "create:haunting",
  "ingredients": [
    {
      "item": "garnished:carnotite"
    }
  ],
  "results": [
    {
      "item": "create:ochrum"
    }
  ]
}